[{"name":"applebloom","slug":"applebloom","path":"emotes/100x100/applebloom","children":[{"name":"1_0071_b08_abwut.jpg","slug":"1_0071_b08_abwut"},{"name":"1_0087_a32_abmeh.jpg","slug":"1_0087_a32_abmeh"},{"name":"1_0093_a26_abbored.jpg","slug":"1_0093_a26_abbored"},{"name":"1_0159_h00_abgrump.jpg","slug":"1_0159_h00_abgrump"},{"name":"1_0183_g16_abteehee.jpg","slug":"1_0183_g16_abteehee"},{"name":"1_0235_f05_abstern.jpg","slug":"1_0235_f05_abstern"},{"name":"1_0263_e17_abhuh.jpg","slug":"1_0263_e17_abhuh"},{"name":"1_0266_e14_absmile.jpg","slug":"1_0266_e14_absmile"}]},{"name":"applejack","slug":"applejack","path":"emotes/100x100/applejack","children":[{"name":"1_0025_c14_hmmm.jpg","slug":"1_0025_c14_hmmm"},{"name":"1_0035_c04_ajfrown.jpg","slug":"1_0035_c04_ajfrown"},{"name":"1_0055_b24_squintyjack.jpg","slug":"1_0055_b24_squintyjack"},{"name":"1_0058_b21_eeyup.jpg","slug":"1_0058_b21_eeyup"},{"name":"1_0068_b11_ajsly.jpg","slug":"1_0068_b11_ajsly"},{"name":"1_0072_b07_ajwut.jpg","slug":"1_0072_b07_ajwut"},{"name":"1_0074_b05_ajugh.jpg","slug":"1_0074_b05_ajugh"},{"name":"1_0078_b01_ajcower.jpg","slug":"1_0078_b01_ajcower"},{"name":"1_0080_a39_applederp.jpg","slug":"1_0080_a39_applederp"},{"name":"1_0082_a37_applegasp.jpg","slug":"1_0082_a37_applegasp"},{"name":"1_0091_a28_grannysmith.jpg","slug":"1_0091_a28_grannysmith"},{"name":"1_0095_a24_swagintosh.jpg","slug":"1_0095_a24_swagintosh"},{"name":"1_0114_a05_ajsup.jpg","slug":"1_0114_a05_ajsup"},{"name":"1_0116_a03_ajhappy.jpg","slug":"1_0116_a03_ajhappy"},{"name":"1_0119_a00_ajlie.jpg","slug":"1_0119_a00_ajlie"},{"name":"1_0142_h17_ajpuzzle.jpg","slug":"1_0142_h17_ajpuzzle"},{"name":"1_0167_g32_ajeesh.jpg","slug":"1_0167_g32_ajeesh"},{"name":"1_0173_g26_appleroll.jpg","slug":"1_0173_g26_appleroll"},{"name":"1_0203_f36_ajgrump.jpg","slug":"1_0203_f36_ajgrump"},{"name":"1_0220_f20_ajdoubt.jpg","slug":"1_0220_f20_ajdoubt"},{"name":"1_0233_f07_ajcry.jpg","slug":"1_0233_f07_ajcry"},{"name":"1_0251_e29_macintears.jpg","slug":"1_0251_e29_macintears"},{"name":"1_0273_e07_ajbaffle.jpg","slug":"1_0273_e07_ajbaffle"}]},{"name":"cadance","slug":"cadance","path":"emotes/100x100/cadance","children":[{"name":"1_0003_c36_shinigpride.jpg","slug":"1_0003_c36_shinigpride"},{"name":"1_0004_c35_cadancesmile.jpg","slug":"1_0004_c35_cadancesmile"},{"name":"1_0090_a29_cadance.jpg","slug":"1_0090_a29_cadance"},{"name":"1_0110_a09_shiningarmor.jpg","slug":"1_0110_a09_shiningarmor"},{"name":"1_0138_h21_shiningsmug.jpg","slug":"1_0138_h21_shiningsmug"}]},{"name":"celestia","slug":"celestia","path":"emotes/100x100/celestia","children":[{"name":"1_0021_c18_celestia.jpg","slug":"1_0021_c18_celestia"},{"name":"1_0101_a18_celestiawut.jpg","slug":"1_0101_a18_celestiawut"},{"name":"1_0108_a11_celestiamad.jpg","slug":"1_0108_a11_celestiamad"},{"name":"1_0157_h02_celestiasquint.jpg","slug":"1_0157_h02_celestiasquint"},{"name":"1_0158_h01_celestiawink.jpg","slug":"1_0158_h01_celestiawink"},{"name":"1_0180_g19_celestiahappy.jpg","slug":"1_0180_g19_celestiahappy"},{"name":"1_0191_g08_celestiahurt.jpg","slug":"1_0191_g08_celestiahurt"}]},{"name":"derpy","slug":"derpy","path":"emotes/100x100/derpy","children":[{"name":"1_0013_c26_derpyshocked.jpg","slug":"1_0013_c26_derpyshocked"},{"name":"1_0014_c25_derp.jpg","slug":"1_0014_c25_derp"},{"name":"1_0016_c23_derpyhappy.jpg","slug":"1_0016_c23_derpyhappy"},{"name":"1_0097_a22_derpwizard.jpg","slug":"1_0097_a22_derpwizard"}]},{"name":"discord","slug":"discord","path":"emotes/100x100/discord","children":[{"name":"1_0109_a10_priceless.jpg","slug":"1_0109_a10_priceless"},{"name":"1_0227_f13_discordgrump.jpg","slug":"1_0227_f13_discordgrump"},{"name":"1_0248_e32_discordsad.jpg","slug":"1_0248_e32_discordsad"}]},{"name":"fluttershy","slug":"fluttershy","path":"emotes/100x100/fluttershy","children":[{"name":"1_0002_c37_fluttercry.jpg","slug":"1_0002_c37_fluttercry"},{"name":"1_0005_c34_whattheflut.jpg","slug":"1_0005_c34_whattheflut"},{"name":"1_0011_c28_angel.jpg","slug":"1_0011_c28_angel"},{"name":"1_0022_c17_loveme.jpg","slug":"1_0022_c17_loveme"},{"name":"1_0036_c03_flutterblush.jpg","slug":"1_0036_c03_flutterblush"},{"name":"1_0049_b30_fluttershy.jpg","slug":"1_0049_b30_fluttershy"},{"name":"1_0063_b16_flutterwink.jpg","slug":"1_0063_b16_flutterwink"},{"name":"1_0065_b14_flutteryay.jpg","slug":"1_0065_b14_flutteryay"},{"name":"1_0075_b04_fluttershh.jpg","slug":"1_0075_b04_fluttershh"},{"name":"1_0077_b02_fluttersrs.jpg","slug":"1_0077_b02_fluttersrs"},{"name":"1_0079_b00_flutterfear.jpg","slug":"1_0079_b00_flutterfear"},{"name":"1_0089_a30_flutterroll.jpg","slug":"1_0089_a30_flutterroll"},{"name":"1_0099_a20_flutterjerk.jpg","slug":"1_0099_a20_flutterjerk"},{"name":"1_0104_a15_flutterwhoa.jpg","slug":"1_0104_a15_flutterwhoa"},{"name":"1_0126_h33_flutterball.jpg","slug":"1_0126_h33_flutterball"},{"name":"1_0165_g34_flutternope.jpg","slug":"1_0165_g34_flutternope"},{"name":"1_0186_g13_flutterplz.jpg","slug":"1_0186_g13_flutterplz"},{"name":"1_0192_g07_flutterbrow.jpg","slug":"1_0192_g07_flutterbrow"},{"name":"1_0205_f34_flutternice.jpg","slug":"1_0205_f34_flutternice"},{"name":"1_0209_f30_flutterhay.jpg","slug":"1_0209_f30_flutterhay"},{"name":"1_0231_f09_flutterkay.jpg","slug":"1_0231_f09_flutterkay"}]},{"name":"luna","slug":"luna","path":"emotes/100x100/luna","children":[{"name":"1_0012_c27_lunagasp.jpg","slug":"1_0012_c27_lunagasp"},{"name":"1_0023_c16_lunasad.jpg","slug":"1_0023_c16_lunasad"},{"name":"1_0107_a12_lunawait.jpg","slug":"1_0107_a12_lunawait"},{"name":"1_0117_a02_lunateehee.jpg","slug":"1_0117_a02_lunateehee"},{"name":"1_0179_g20_lunagrump.jpg","slug":"1_0179_g20_lunagrump"},{"name":"1_0207_f32_nightmaregrin.jpg","slug":"1_0207_f32_nightmaregrin"},{"name":"1_0249_e31_lunamad.jpg","slug":"1_0249_e31_lunamad"},{"name":"1_0268_e12_happyluna.jpg","slug":"1_0268_e12_happyluna"},{"name":"1_0275_e05_nmm.jpg","slug":"1_0275_e05_nmm"}]},{"name":"other","slug":"other","path":"emotes/100x100/other","children":[{"name":"1_0008_c31_changeling.jpg","slug":"1_0008_c31_changeling"},{"name":"1_0010_c29_photofinish.jpg","slug":"1_0010_c29_photofinish"},{"name":"1_0020_c19_zecora.jpg","slug":"1_0020_c19_zecora"},{"name":"1_0046_b33_dj.jpg","slug":"1_0046_b33_dj"},{"name":"1_0051_b28_cockatrice.jpg","slug":"1_0051_b28_cockatrice"},{"name":"1_0084_a35_silverspoon.jpg","slug":"1_0084_a35_silverspoon"},{"name":"1_0100_a19_chrysalis.jpg","slug":"1_0100_a19_chrysalis"},{"name":"1_0122_rapathia.jpg","slug":"1_0122_rapathia"},{"name":"1_0124_ocelus.jpg","slug":"1_0124_ocelus"},{"name":"1_0125_ocelllus.jpg","slug":"1_0125_ocelllus"},{"name":"1_0161_g38_sunburstnervous.jpg","slug":"1_0161_g38_sunburstnervous"},{"name":"1_0168_g31_skystarfine.jpg","slug":"1_0168_g31_skystarfine"},{"name":"1_0174_g25_squeestar.jpg","slug":"1_0174_g25_squeestar"},{"name":"1_0185_g14_emberwtf.jpg","slug":"1_0185_g14_emberwtf"},{"name":"1_0194_g05_quibble.jpg","slug":"1_0194_g05_quibble"},{"name":"1_0195_g04_cococold.jpg","slug":"1_0195_g04_cococold"},{"name":"1_0198_g01_discentiajudge.jpg","slug":"1_0198_g01_discentiajudge"},{"name":"1_0199_g00_karma.jpg","slug":"1_0199_g00_karma"},{"name":"1_0212_f27_limestonegrin.jpg","slug":"1_0212_f27_limestonegrin"},{"name":"1_0214_f25_cocosmile.jpg","slug":"1_0214_f25_cocosmile"},{"name":"1_0215_f24a_flam.jpg","slug":"1_0215_f24a_flam"},{"name":"1_0216_f24_flim.jpg","slug":"1_0216_f24_flim"},{"name":"1_0218_f22_wasntme.jpg","slug":"1_0218_f22_wasntme"},{"name":"1_0224_f16_thcalm.jpg","slug":"1_0224_f16_thcalm"},{"name":"1_0226_f14_troubleshoes.jpg","slug":"1_0226_f14_troubleshoes"},{"name":"1_0229_f11_bulkbiceps.jpg","slug":"1_0229_f11_bulkbiceps"},{"name":"1_0236_f04_guard.jpg","slug":"1_0236_f04_guard"},{"name":"1_0238_f02_sombra.jpg","slug":"1_0238_f02_sombra"},{"name":"1_0253_e27_thehorror.jpg","slug":"1_0253_e27_thehorror"},{"name":"1_0254_e26_cheerilee.jpg","slug":"1_0254_e26_cheerilee"},{"name":"1_0256_e24_dealwithit.jpg","slug":"1_0256_e24_dealwithit"},{"name":"1_0257_e23_berry.jpg","slug":"1_0257_e23_berry"},{"name":"1_0258_e22_sotrue.jpg","slug":"1_0258_e22_sotrue"},{"name":"1_0259_e21_spitfire.jpg","slug":"1_0259_e21_spitfire"},{"name":"1_0260_e20_snails.jpg","slug":"1_0260_e20_snails"},{"name":"1_0261_e19_discentia.jpg","slug":"1_0261_e19_discentia"},{"name":"1_0264_e16_colgate.jpg","slug":"1_0264_e16_colgate"},{"name":"1_0265_e15_whooves.jpg","slug":"1_0265_e15_whooves"},{"name":"1_0269_e11_bonbon.jpg","slug":"1_0269_e11_bonbon"},{"name":"1_0271_e09_gilda.jpg","slug":"1_0271_e09_gilda"},{"name":"1_0274_e06_octavia.jpg","slug":"1_0274_e06_octavia"},{"name":"1_0279_e01_lyra.jpg","slug":"1_0279_e01_lyra"},{"name":"1_0281_changedling.jpg","slug":"1_0281_changedling"}]},{"name":"pinkie","slug":"pinkie","path":"emotes/100x100/pinkie","children":[{"name":"1_0000_c39_ppreally.jpg","slug":"1_0000_c39_ppreally"},{"name":"1_0000_f00_pinkiesad.jpg","slug":"1_0000_f00_pinkiesad"},{"name":"1_0015_c24_joy.jpg","slug":"1_0015_c24_joy"},{"name":"1_0017_c22_hahaha.jpg","slug":"1_0017_c22_hahaha"},{"name":"1_0027_c12_party.jpg","slug":"1_0027_c12_party"},{"name":"1_0032_c07_pinkamina.jpg","slug":"1_0032_c07_pinkamina"},{"name":"1_0037_c02_ohhi.jpg","slug":"1_0037_c02_ohhi"},{"name":"1_0040_b39_ppseesyou.jpg","slug":"1_0040_b39_ppseesyou"},{"name":"1_0069_b10_ppboring.jpg","slug":"1_0069_b10_ppboring"},{"name":"1_0076_b03_pinkieshrug.jpg","slug":"1_0076_b03_pinkieshrug"},{"name":"1_0085_a34_pinkieawe.jpg","slug":"1_0085_a34_pinkieawe"},{"name":"1_0103_a16_ppcute.jpg","slug":"1_0103_a16_ppcute"},{"name":"1_0106_a13_pinkiefear.jpg","slug":"1_0106_a13_pinkiefear"},{"name":"1_0123_pinki.jpg","slug":"1_0123_pinki"},{"name":"1_0128_h31_pinkiesmug.jpg","slug":"1_0128_h31_pinkiesmug"},{"name":"1_0141_h18_pinkieeager.jpg","slug":"1_0141_h18_pinkieeager"},{"name":"1_0163_g36_pinkiesmoosh.jpg","slug":"1_0163_g36_pinkiesmoosh"},{"name":"1_0166_g33_pinkiesugar.jpg","slug":"1_0166_g33_pinkiesugar"},{"name":"1_0170_g29_squeekiepie.jpg","slug":"1_0170_g29_squeekiepie"},{"name":"1_0196_g03_pinkie.jpg","slug":"1_0196_g03_pinkie"},{"name":"1_0200_f39_gummystare.jpg","slug":"1_0200_f39_gummystare"},{"name":"1_0204_f35_ppdont.jpg","slug":"1_0204_f35_ppdont"},{"name":"1_0223_f17_ooh.jpg","slug":"1_0223_f17_ooh"},{"name":"1_0246_e34_pinkiepout.jpg","slug":"1_0246_e34_pinkiepout"},{"name":"1_0247_e33_maud.jpg","slug":"1_0247_e33_maud"},{"name":"1_0276_e04_huhhuh.jpg","slug":"1_0276_e04_huhhuh"}]},{"name":"rainbowdash","slug":"rainbowdash","path":"emotes/100x100/rainbowdash","children":[{"name":"1_0007_c32_rdscared.jpg","slug":"1_0007_c32_rdscared"},{"name":"1_0019_c20_rdannoyed.jpg","slug":"1_0019_c20_rdannoyed"},{"name":"1_0026_c13_gross.jpg","slug":"1_0026_c13_gross"},{"name":"1_0029_c10_rdhappy.jpg","slug":"1_0029_c10_rdhappy"},{"name":"1_0033_c06_louder.jpg","slug":"1_0033_c06_louder"},{"name":"1_0039_c00_rdsitting.jpg","slug":"1_0039_c00_rdsitting"},{"name":"1_0042_b37_rdcool.jpg","slug":"1_0042_b37_rdcool"},{"name":"1_0043_b36_soawesome.jpg","slug":"1_0043_b36_soawesome"},{"name":"1_0047_b32_rdwut.jpg","slug":"1_0047_b32_rdwut"},{"name":"1_0048_b31_rdsmile.jpg","slug":"1_0048_b31_rdsmile"},{"name":"1_0094_a25_rdcry.jpg","slug":"1_0094_a25_rdcry"},{"name":"1_0132_h27_rdeyy.jpg","slug":"1_0132_h27_rdeyy"},{"name":"1_0181_g18_rdsup.jpg","slug":"1_0181_g18_rdsup"},{"name":"1_0193_g06_rdthis.jpg","slug":"1_0193_g06_rdthis"},{"name":"1_0221_f19_notangry.jpg","slug":"1_0221_f19_notangry"},{"name":"1_0225_f15_rdsnrk.jpg","slug":"1_0225_f15_rdsnrk"},{"name":"1_0252_e28_awwyeah.jpg","slug":"1_0252_e28_awwyeah"},{"name":"1_0255_e25_rdsalute.jpg","slug":"1_0255_e25_rdsalute"},{"name":"1_0270_e10_rdhuh.jpg","slug":"1_0270_e10_rdhuh"}]},{"name":"rarity","slug":"rarity","path":"emotes/100x100/rarity","children":[{"name":"1_0024_c15_fabulous.jpg","slug":"1_0024_c15_fabulous"},{"name":"1_0034_c05_raritysad.jpg","slug":"1_0034_c05_raritysad"},{"name":"1_0044_b35_raritywhy.jpg","slug":"1_0044_b35_raritywhy"},{"name":"1_0052_b27_raritywhine.jpg","slug":"1_0052_b27_raritywhine"},{"name":"1_0053_b26_rarityannoyed.jpg","slug":"1_0053_b26_rarityannoyed"},{"name":"1_0059_b20_rarityyell.jpg","slug":"1_0059_b20_rarityyell"},{"name":"1_0060_b19_rarityprimp.jpg","slug":"1_0060_b19_rarityprimp"},{"name":"1_0064_b15_raritywut.jpg","slug":"1_0064_b15_raritywut"},{"name":"1_0067_b12_raritydress.jpg","slug":"1_0067_b12_raritydress"},{"name":"1_0070_b09_rarityjudge.jpg","slug":"1_0070_b09_rarityjudge"},{"name":"1_0081_a38_rarishock.jpg","slug":"1_0081_a38_rarishock"},{"name":"1_0083_a36_rarityreally.jpg","slug":"1_0083_a36_rarityreally"},{"name":"1_0112_a07_raritynews.jpg","slug":"1_0112_a07_raritynews"},{"name":"1_0115_a04_raritydaww.jpg","slug":"1_0115_a04_raritydaww"},{"name":"1_0137_h22_rarischeme.jpg","slug":"1_0137_h22_rarischeme"},{"name":"1_0201_f38_raritysquee.jpg","slug":"1_0201_f38_raritysquee"},{"name":"1_0211_f28_raritygrump.jpg","slug":"1_0211_f28_raritygrump"},{"name":"1_0222_f18_raritytired.jpg","slug":"1_0222_f18_raritytired"},{"name":"1_0232_f08_rarityeww.jpg","slug":"1_0232_f08_rarityeww"},{"name":"1_0277_e03_wahaha.jpg","slug":"1_0277_e03_wahaha"}]},{"name":"scootaloo","slug":"scootaloo","path":"emotes/100x100/scootaloo","children":[{"name":"1_0001_e38_scootablue.jpg","slug":"1_0001_e38_scootablue"},{"name":"1_0031_c08_scootaloo.jpg","slug":"1_0031_c08_scootaloo"},{"name":"1_0086_a33_scootaderp.jpg","slug":"1_0086_a33_scootaderp"},{"name":"1_0092_a27_scootaplease.jpg","slug":"1_0092_a27_scootaplease"},{"name":"1_0105_a14_scootacheer.jpg","slug":"1_0105_a14_scootacheer"},{"name":"1_0127_h32_peekaloo.jpg","slug":"1_0127_h32_peekaloo"},{"name":"1_0135_h24_scootaglance.jpg","slug":"1_0135_h24_scootaglance"},{"name":"1_0213_f26_skeptiloo.jpg","slug":"1_0213_f26_skeptiloo"},{"name":"1_0228_f12_scootaeww.jpg","slug":"1_0228_f12_scootaeww"},{"name":"1_0278_e02_cutealoo.jpg","slug":"1_0278_e02_cutealoo"}]},{"name":"serve.js","slug":"serve"},{"name":"spike","slug":"spike","path":"emotes/100x100/spike","children":[{"name":"1_0030_c09_allmybits.jpg","slug":"1_0030_c09_allmybits"},{"name":"1_0045_b34_spikepushy.jpg","slug":"1_0045_b34_spikepushy"},{"name":"1_0056_b23_noooo.jpg","slug":"1_0056_b23_noooo"},{"name":"1_0057_b22_takealetter.jpg","slug":"1_0057_b22_takealetter"},{"name":"1_0061_b18_manspike.jpg","slug":"1_0061_b18_manspike"},{"name":"1_0066_b13_spikenervous.jpg","slug":"1_0066_b13_spikenervous"},{"name":"1_0088_a31_spikemeh.jpg","slug":"1_0088_a31_spikemeh"},{"name":"1_0160_g39_spikewoke.jpg","slug":"1_0160_g39_spikewoke"},{"name":"1_0172_g27_spikeholdup.jpg","slug":"1_0172_g27_spikeholdup"},{"name":"1_0206_f33_spikeapproves.jpg","slug":"1_0206_f33_spikeapproves"},{"name":"1_0219_f21_spikeholdup.jpg","slug":"1_0219_f21_spikeholdup"},{"name":"1_0241_e39_spikehappy.jpg","slug":"1_0241_e39_spikehappy"},{"name":"1_0262_e18_spikewtf.jpg","slug":"1_0262_e18_spikewtf"}]},{"name":"starlight","slug":"starlight","path":"emotes/100x100/starlight","children":[{"name":"1_0003_f29_goodjob.jpg","slug":"1_0003_f29_goodjob"},{"name":"1_0133_h26_starlightsly.jpg","slug":"1_0133_h26_starlightsly"},{"name":"1_0151_h08_starlightisee.jpg","slug":"1_0151_h08_starlightisee"},{"name":"1_0162_g37_starlightspittle.jpg","slug":"1_0162_g37_starlightspittle"},{"name":"1_0178_g21_sgeesh.jpg","slug":"1_0178_g21_sgeesh"},{"name":"1_0182_g17_squintyglam.jpg","slug":"1_0182_g17_squintyglam"},{"name":"1_0188_g11_sgsneaky.jpg","slug":"1_0188_g11_sgsneaky"},{"name":"1_0190_g09_sgconcern.jpg","slug":"1_0190_g09_sgconcern"},{"name":"1_0202_f37_sgpopcorn.jpg","slug":"1_0202_f37_sgpopcorn"},{"name":"1_0230_f10_starlightrage.jpg","slug":"1_0230_f10_starlightrage"}]},{"name":"students","slug":"students","path":"emotes/100x100/students","children":[{"name":"1_0131_h28_galluswtf.jpg","slug":"1_0131_h28_galluswtf"},{"name":"1_0134_h25_crazyglow.jpg","slug":"1_0134_h25_crazyglow"},{"name":"1_0139_h20_cozyglow.jpg","slug":"1_0139_h20_cozyglow"},{"name":"1_0143_h16_silverstream.jpg","slug":"1_0143_h16_silverstream"},{"name":"1_0146_h13_ocellus.jpg","slug":"1_0146_h13_ocellus"},{"name":"1_0147_h12_silverbored.jpg","slug":"1_0147_h12_silverbored"},{"name":"1_0148_h11_sandbaruhh.jpg","slug":"1_0148_h11_sandbaruhh"},{"name":"1_0149_h10_gallus.jpg","slug":"1_0149_h10_gallus"},{"name":"1_0150_h09_yona.jpg","slug":"1_0150_h09_yona"}]},{"name":"sunset","slug":"sunset","path":"emotes/100x100/sunset","children":[{"name":"1_0155_h04_sunspicious.jpg","slug":"1_0155_h04_sunspicious"},{"name":"1_0156_h03_sunsetgrump.jpg","slug":"1_0156_h03_sunsetgrump"},{"name":"1_0184_g15_sunsetwhyme.jpg","slug":"1_0184_g15_sunsetwhyme"},{"name":"1_0243_e37_sunsetsneaky.jpg","slug":"1_0243_e37_sunsetsneaky"},{"name":"1_0244_e36_sunsetshimmer.jpg","slug":"1_0244_e36_sunsetshimmer"}]},{"name":"sweetiebelle","slug":"sweetiebelle","path":"emotes/100x100/sweetiebelle","children":[{"name":"1_0001_c38_sneakybelle.jpg","slug":"1_0001_c38_sneakybelle"},{"name":"1_0054_b25_dumbfabric.jpg","slug":"1_0054_b25_dumbfabric"},{"name":"1_0102_a17_sbbook.jpg","slug":"1_0102_a17_sbbook"},{"name":"1_0113_a06_ohcomeon.jpg","slug":"1_0113_a06_ohcomeon"},{"name":"1_0189_g10_sbfocus.jpg","slug":"1_0189_g10_sbfocus"},{"name":"1_0208_f31_sbwtf.jpg","slug":"1_0208_f31_sbwtf"},{"name":"1_0267_e13_sbstare.jpg","slug":"1_0267_e13_sbstare"}]},{"name":"tempest","slug":"tempest","path":"emotes/100x100/tempest","children":[{"name":"1_0171_g28_tempestgaze.jpg","slug":"1_0171_g28_tempestgaze"},{"name":"1_0175_g24_tempestsmile.jpg","slug":"1_0175_g24_tempestsmile"},{"name":"1_0176_g23_tempest.jpg","slug":"1_0176_g23_tempest"}]},{"name":"trixie","slug":"trixie","path":"emotes/100x100/trixie","children":[{"name":"1_0009_c30_trixiesad.jpg","slug":"1_0009_c30_trixiesad"},{"name":"1_0073_b06_trixiesmug.jpg","slug":"1_0073_b06_trixiesmug"},{"name":"1_0140_h19_trixiecheer.jpg","slug":"1_0140_h19_trixiecheer"},{"name":"1_0187_g12_trixieww.jpg","slug":"1_0187_g12_trixieww"},{"name":"1_0280_e00_fillytgap.jpg","slug":"1_0280_e00_fillytgap"}]},{"name":"twilight","slug":"twilight","path":"emotes/100x100/twilight","children":[{"name":"1_0002_e35_twisecret.jpg","slug":"1_0002_e35_twisecret"},{"name":"1_0006_c33_twidaww.jpg","slug":"1_0006_c33_twidaww"},{"name":"1_0018_c21_twistare.jpg","slug":"1_0018_c21_twistare"},{"name":"1_0028_c11_twismile.jpg","slug":"1_0028_c11_twismile"},{"name":"1_0038_c01_twismug.jpg","slug":"1_0038_c01_twismug"},{"name":"1_0041_b38_facehoof.jpg","slug":"1_0041_b38_facehoof"},{"name":"1_0050_b29_twirage.jpg","slug":"1_0050_b29_twirage"},{"name":"1_0062_b17_twisquint.jpg","slug":"1_0062_b17_twisquint"},{"name":"1_0096_a23_twibeam.jpg","slug":"1_0096_a23_twibeam"},{"name":"1_0098_a21_twicrazy.jpg","slug":"1_0098_a21_twicrazy"},{"name":"1_0111_a08_twiright.jpg","slug":"1_0111_a08_twiright"},{"name":"1_0118_a01_twipride.jpg","slug":"1_0118_a01_twipride"},{"name":"1_0130_h29_twifret.jpg","slug":"1_0130_h29_twifret"},{"name":"1_0136_h23_twipudding.jpg","slug":"1_0136_h23_twipudding"},{"name":"1_0153_h06_twiomg.jpg","slug":"1_0153_h06_twiomg"},{"name":"1_0154_h05_twicoffee.jpg","slug":"1_0154_h05_twicoffee"},{"name":"1_0164_g35_twishame.jpg","slug":"1_0164_g35_twishame"},{"name":"1_0169_g30_twisheepish.jpg","slug":"1_0169_g30_twisheepish"},{"name":"1_0177_g22_twieek.jpg","slug":"1_0177_g22_twieek"},{"name":"1_0197_g02_twisnide.jpg","slug":"1_0197_g02_twisnide"},{"name":"1_0217_f23_twipbbt.jpg","slug":"1_0217_f23_twipbbt"},{"name":"1_0250_e30_twisad.jpg","slug":"1_0250_e30_twisad"},{"name":"1_0272_e08_twiponder.jpg","slug":"1_0272_e08_twiponder"}]},{"name":"yark","slug":"yark","path":"emotes/100x100/yark","children":[{"name":"1_0120_YAK.jpg","slug":"1_0120_yak"},{"name":"1_0152_h07_yak.jpg","slug":"1_0152_h07_yak"}]}]